hardeneks/__init__.py
hardeneks/cluster_wide/__init__.py
hardeneks/cluster_wide/cluster_autoscaling/__init__.py
hardeneks/cluster_wide/cluster_autoscaling/cluster_autoscaler.py
hardeneks/cluster_wide/reliability/__init__.py
hardeneks/cluster_wide/reliability/applications.py
hardeneks/cluster_wide/scalability/__init__.py
hardeneks/cluster_wide/scalability/control_plane.py
hardeneks/cluster_wide/scalability/skipped.json
hardeneks/cluster_wide/security/__init__.py
hardeneks/cluster_wide/security/detective_controls.py
hardeneks/cluster_wide/security/encryption_secrets.py
hardeneks/cluster_wide/security/iam.py
hardeneks/cluster_wide/security/image_security.py
hardeneks/cluster_wide/security/infrastructure_security.py
hardeneks/cluster_wide/security/multi_tenancy.py
hardeneks/cluster_wide/security/network_security.py
hardeneks/cluster_wide/security/pod_security.py
hardeneks/config.yaml
hardeneks/harden.py
hardeneks/helpers.py
hardeneks/namespace_based/__init__.py
hardeneks/namespace_based/reliability/__init__.py
hardeneks/namespace_based/reliability/applications.py
hardeneks/namespace_based/security/__init__.py
hardeneks/namespace_based/security/encryption_secrets.py
hardeneks/namespace_based/security/iam.py
hardeneks/namespace_based/security/network_security.py
hardeneks/namespace_based/security/pod_security.py
hardeneks/namespace_based/security/runtime_security.py
hardeneks/resources.py
hardeneks/rules.py
hardeneks-0.11.2.dist-info/LICENSE
hardeneks-0.11.2.dist-info/METADATA
hardeneks-0.11.2.dist-info/WHEEL
hardeneks-0.11.2.dist-info/entry_points.txt
hardeneks-0.11.2.dist-info/RECORD
