Metadata-Version: 2.1
Name: hardeneks
Version: 0.11.2
Summary: 
Author: Doruk Ozturk
Author-email: dozturk@amazon.com
Requires-Python: >=3.8,<4.0
Classifier: Programming Language :: Python :: 3
Classifier: Programming Language :: Python :: 3.8
Classifier: Programming Language :: Python :: 3.9
Classifier: Programming Language :: Python :: 3.10
Classifier: Programming Language :: Python :: 3.11
Classifier: Programming Language :: Python :: 3.12
Classifier: Programming Language :: Python :: 3.13
Requires-Dist: boto3 (>=1.26.2,<2.0.0)
Requires-Dist: kubernetes (>=25.3.0,<26.0.0)
Requires-Dist: pre-commit (>=2.20.0,<3.0.0)
Requires-Dist: tox-gh-actions (>=3.0.0,<4.0.0)
Requires-Dist: typer[all] (>=0.6.1,<0.7.0)
